<?xml version="1.0" encoding="ISO-8859-1"?>
<Room class="barebones.world.data.ObjectDetailBean">
    <id class="java.lang.String">Room</id>
    <cmdKeyMap class="java.util.HashMap"/>
    <containedItemSet class="java.util.HashSet"/>
    <objKeyMap class="java.util.HashMap">
        <map-item-val class="barebones.world.data.ResponseContentBean" key="room.onepsgmsg">
            <text class="java.lang.String">There is a passage %s</text>
        </map-item-val>
        <map-item-val class="barebones.world.data.ResponseContentBean" key="room.multipsgmsg">
            <text class="java.lang.String">There are passages %s</text>
        </map-item-val>
        <map-item-val class="barebones.world.data.ResponseContentBean" key="room.notvaliddirmsg">
            <text class="java.lang.String">%s is not a valid direction</text>
        </map-item-val>
        <map-item-val class="barebones.world.data.ResponseContentBean" key="room.invaliddirtxt">
            <text class="java.lang.String">There is no passage %s</text>
        </map-item-val>
        <map-item-val class="barebones.world.data.ResponseContentBean" key="room.movetxt">
            <text class="java.lang.String">You amble %s.</text>
        </map-item-val>
    </objKeyMap>
</Room>
